{
  "kind": "singleType",
  "collectionName": "resumes",
  "info": {
    "singularName": "resume",
    "pluralName": "resumes",
    "displayName": "Resume",
    "description": ""
  },
  "options": {
    "draftAndPublish": true
  },
  "pluginOptions": {},
  "attributes": {
    "hero": {
      "type": "component",
      "repeatable": true,
      "component": "sections.hero"
    },
    "contact": {
      "displayName": "address",
      "type": "component",
      "repeatable": false,
      "component": "sections.address"
    },
    "description": {
      "type": "richtext",
      "required": true
    },
    "image": {
      "type": "media",
      "multiple": false,
      "required": false,
      "allowedTypes": [
        "images"
      ]
    },
    "skills": {
      "type": "richtext"
    },
    "interests": {
      "type": "richtext"
    },
    "experience": {
      "displayName": "experience",
      "type": "component",
      "repeatable": true,
      "component": "resume.experience"
    },
    "links": {
      "displayName": "footerLinks",
      "type": "component",
      "repeatable": true,
      "component": "resume.footer-links"
    }
  }
}
